voltage.v
module voltage(v_therm, temp_therm);
    input [31:0] v_therm;
    output [31:0] temp_therm;

    // real v1;
    // assign v1 = v_therm;

    wire [31:0] w1, w2, w3, w4, w5, w6, R, R_ext, B, T0, R0;
    // 0000000000000000 
    // initial begin
    //     T0 <= 25;
    //     R0 <= 3539;
    //     B <= 10000;
    //     w1 <= 10000;
    //     w2 <= 3;
        
    //     w4 <= v_therm / w2;
    //     w5 <= 1 + w4;
    //     w6 <= w3 * w5;

    //     R <= w6*v_therm; // R
    //     R_ext <= R * 100000;

    // end
    // real_div real_div(.a(w1), .b(w2), .c(w3));
    assign T0 = 32'd25; // 25 = 011001 , R0
    assign R0 = 32'b000000000000000000011111010000;   // 2000 
    assign B = 32'b000000000000000000110111010011;   // 3539 , B
    assign w1 = 32'b000000000000000010011100010000; //10000
    assign w2 = 32'b000000000000000000000000000011_01;   // 3.25 .. technically 3.3 tho

    assign w3 = w1 / w2;
    assign w4 = v_therm / w2;
    assign w5 = 1 + w4;
    assign w6 = w3 * w5;

    assign R = w6*v_therm; // R
    assign R_ext = R * 10000;

    wire [31:0] q1, q2, q3, q4, q5, q6, q7;
    // initial begin
    //     q1 <= R_ext / R0;
    //     q2 <= $ln(q1);
    //     q3 <= q2 / B;
    //     q4 <= q3 + q5;
    //     q5 <= 1 / T0;
    //     q6 <= q4 + q5; 
    //     q7 <= 1 / q6;
    // end
    assign q1 = (R_ext / R0) + 1;
    assign q2 = $ln(q1) * 10000;
    assign q3 = q2 / B;
    assign q4 = q3 + q5;
    assign q5 = 1 / T0;
    assign q6 = q4 + q5; 
    assign temp_therm = q6;
    // assign temp_therm = 1 / q6; // T
    // assign temp_therm = R / 150; // to at least have output
endmodule

voltage_tb.v
`timescale 1 ns / 100 ps
module voltage_tb;

    reg [31:0] input_voltage; // input
    wire [31:0] output_temp; // output

    voltage voltage(.v_therm(input_voltage), .temp_therm(output_temp));

    // initialize
    initial begin
        input_voltage = 0;

        // Output file name
		$dumpfile("voltage.vcd");
		// Module to capture and what level, 0 means all wires
		$dumpvars(0, voltage_tb);

        #80
        $finish;
    end

    always 
        #10 input_voltage += 1;

    always @(input_voltage) begin
        #1;
        $display("input_voltage:%d ---> output_temp:%d", input_voltage, output_temp);
    end

    
endmodule

voltage.vcd
$date
	Tue Apr 20 16:33:24 2021
$end
$version
	Icarus Verilog
$end
$timescale
	1ps
$end
$scope module voltage_tb $end
$var wire 32 ! output_temp [31:0] $end
$var reg 32 " input_voltage [31:0] $end
$scope module voltage $end
$var wire 32 # B [31:0] $end
$var wire 32 $ R0 [31:0] $end
$var wire 32 % T0 [31:0] $end
$var wire 32 & temp_therm [31:0] $end
$var wire 32 ' v_therm [31:0] $end
$var wire 32 ( w1 [31:0] $end
$var wire 32 ) w2 [31:0] $end
$var wire 32 * w6 [31:0] $end
$var wire 32 + w5 [31:0] $end
$var wire 32 , w4 [31:0] $end
$var wire 32 - w3 [31:0] $end
$var wire 32 . q6 [31:0] $end
$var wire 32 / q5 [31:0] $end
$var wire 32 0 q4 [31:0] $end
$var wire 32 1 q3 [31:0] $end
$var wire 32 2 q2 [31:0] $end
$var wire 32 3 q1 [31:0] $end
$var wire 32 4 R_ext [31:0] $end
$var wire 32 5 R [31:0] $end
$upscope $end
$upscope $end
$enddefinitions $end
#0
$dumpvars
b0 5
b0 4
b1 3
b0 2
b0 1
b0 0
b0 /
b0 .
b1100000001 -
b0 ,
b1 +
b1100000001 *
b1101 )
b10011100010000 (
b0 '
b0 &
b11001 %
b11111010000 $
b110111010011 #
b0 "
b0 !
$end
#10000
b10111 !
b10111 &
b10111 .
b10111 0
b10111 1
b10100001001110100 2
b111100000110 3
b11101010101011100010000 4
b1100000001 5
b1 "
b1 '
#20000
b11001 !
b11001 &
b11001 .
b11001 0
b11001 1
b10101110110000110 2
b1111000001011 3
b111010101010111000100000 4
b11000000010 5
b10 "
b10 '
#30000
b11010 !
b11010 &
b11010 .
b11010 0
b11010 1
b10110110101011100 2
b10110100010000 3
b1011000000000010100110000 4
b100100000011 5
b11 "
b11 '
#40000
b11011 !
b11011 &
b11011 .
b11011 0
b11011 1
b10111100010011001 2
b11110000010101 3
b1110101010101110001000000 4
b110000000100 5
b100 "
b100 '
#50000
b11000000101010000 2
b100101100011010 3
b10010010101011001101010000 4
b111100000101 5
b101 "
b101 '
#60000
b11100 !
b11100 &
b11100 .
b11100 0
b11100 1
b11000100001101111 2
b101101000011111 3
b10110000000000101001100000 4
b1001000000110 5
b110 "
b110 '
#70000
b11000111001110101 2
b110100100100100 3
b11001101010110000101110000 4
b1010100000111 5
b111 "
b111 '
#80000
b11101 !
b11101 &
b11101 .
b11101 0
b11101 1
b11001001110101100 2
b111100000101001 3
b11101010101011100010000000 4
b1100000001000 5
b1000 "
b1000 '
