voltage.v
module voltage(v_therm, temp_therm);
    input [3:0] v_therm;
    output [31:0] temp_therm;

    // real v1;
    // assign v1 = v_therm;

    wire [31:0] w1, w2, w3, w4, w5, w6, R, B, T0, R0;
    // 0000000000000000 
    assign T0 = 32'b000000000000000000000000011001; // 25 = 011001 , R0
    assign R0 = 32'b000000000000000000011111010000;   // 2000 
    assign B2 = 32'b000000000000000000110111010011;   // 3539 , B
    assign w1 = 32'b000000000000000010011100010000; //10000
    assign w2 = 32'b000000000000000000000000000011;   // 3.25 .. technically 3.3 tho

    assign w3 = w1 / w2;
    assign w4 = v_therm / w2;
    assign w5 = 1 + w4;
    assign w6 = w3 * w5;

    assign R = w6*v_therm; // R

    wire q1, q2, q3, q4, q5, q6;

    assign q1 = R / R0;
    assign q2 = $ln(q1);
    assign q3 = q2 / B;
    assign q4 = q3 + q5;
    // assign temp_therm = 1 / T0; // T
    assign temp_therm = R / 150; // to at least have output
endmodule

voltage_tb.v
`timescale 1 ns / 100 ps
module voltage_tb;

    reg [3:0] input_voltage; // input
    wire [31:0] output_temp; // output

    voltage voltage(.v_therm(input_voltage), .temp_therm(output_temp));

    // initialize
    initial begin
        input_voltage = 0;

        // Output file name
		$dumpfile("voltage.vcd");
		// Module to capture and what level, 0 means all wires
		$dumpvars(0, voltage_tb);

        #80
        $finish;
    end

    always 
        #10 input_voltage += 1;

    always @(input_voltage) begin
        #1;
        $display("input_voltage:%d ---> output_temp:%d", input_voltage, output_temp);
    end

    
endmodule

voltage.vcd
$date
	Mon Apr 19 15:42:29 2021
$end
$version
	Icarus Verilog
$end
$timescale
	1ps
$end
$scope module voltage_tb $end
$var wire 32 ! output_temp [31:0] $end
$var reg 4 " input_voltage [3:0] $end
$scope module voltage $end
$var wire 32 # B [31:0] $end
$var wire 1 $ B2 $end
$var wire 32 % R0 [31:0] $end
$var wire 32 & T0 [31:0] $end
$var wire 1 ' q5 $end
$var wire 4 ( v_therm [3:0] $end
$var wire 32 ) w1 [31:0] $end
$var wire 32 * w2 [31:0] $end
$var wire 32 + w6 [31:0] $end
$var wire 32 , w5 [31:0] $end
$var wire 32 - w4 [31:0] $end
$var wire 32 . w3 [31:0] $end
$var wire 32 / temp_therm [31:0] $end
$var wire 1 0 q4 $end
$var wire 1 1 q3 $end
$var wire 1 2 q2 $end
$var wire 1 3 q1 $end
$var wire 32 4 R [31:0] $end
$upscope $end
$upscope $end
$enddefinitions $end
#0
$dumpvars
b0 4
03
x2
x1
x0
b0 /
b110100000101 .
b0 -
b1 ,
b110100000101 +
b11 *
b10011100010000 )
b0 (
z'
b11001 &
b11111010000 %
1$
bz #
b0 "
b0 !
$end
#10000
02
13
b10110 !
b10110 /
b110100000101 4
b1 "
b1 (
#20000
b101100 !
b101100 /
b1101000001010 4
b10 "
b10 (
#30000
b1101000001010 +
b10 ,
b1 -
b10000101 !
b10000101 /
b100111000011110 4
b11 "
b11 (
#40000
b10110001 !
b10110001 /
b110100000101000 4
b100 "
b100 (
#50000
x2
03
b11011110 !
b11011110 /
b1000001000110010 4
b101 "
b101 (
#60000
02
13
b10011100001111 +
b11 ,
b10 -
b110001111 !
b110001111 /
b1110101001011010 4
b110 "
b110 (
#70000
x2
03
b111010010 !
b111010010 /
b10001000101101001 4
b111 "
b111 (
#80000
02
13
b1000010101 !
b1000010101 /
b10011100001111000 4
b1000 "
b1000 (
